ShortTextClustering/ITER_DBSCAN.py
ShortTextClustering/__init__.py
ShortTextClustering/evaluation.py
ShortTextClustering/sentenceEmbedding.py
ShortTextClustering-0.1.dist-info/METADATA
ShortTextClustering-0.1.dist-info/WHEEL
ShortTextClustering-0.1.dist-info/top_level.txt
ShortTextClustering-0.1.dist-info/RECORD
