Metadata-Version: 2.1
Name: ShortTextClustering
Version: 0.1
Summary: ITER-DBSCAN Implementation for unbalanced short text and numerical data clustering
Home-page: https://github.com/ajaychatterjee/IntentMining/
Author: Ajay Chatterjee
Author-email: ajay.chatt03@gmail.com
License: UNKNOWN
Platform: UNKNOWN
Requires-Dist: tensorflow (==2.3.1)
Requires-Dist: tensorflow-hub (==0.10.0)
Requires-Dist: scikit-learn (==0.23.2)
Requires-Dist: hdbscan (==0.8.26)
Requires-Dist: pandas (==1.1.4)
Requires-Dist: xlrd (==1.2.0)
Requires-Dist: tqdm
